glasspy_extra/__init__.py
glasspy_extra/load_models.py
glasspy_extra-0.1.0.dist-info/LICENSE
glasspy_extra-0.1.0.dist-info/METADATA
glasspy_extra-0.1.0.dist-info/WHEEL
glasspy_extra-0.1.0.dist-info/top_level.txt
glasspy_extra-0.1.0.dist-info/RECORD
