Metadata-Version: 2.1
Name: glasspy-extra
Version: 0.1.0
Summary: Extra stuff for GlassPy 
Home-page: https://github.com/drcassar/glasspy_extra
Author: Daniel Roberto Cassar
Author-email: daniel.r.cassar@gmail.com
License: GPL
Keywords: glass,non-crystalline materials
Classifier: Programming Language :: Python :: 3.9
Classifier: Programming Language :: Python :: 3.10
Classifier: License :: OSI Approved :: GNU General Public License v3 or later (GPLv3+)
Classifier: Operating System :: OS Independent
Classifier: Development Status :: 3 - Alpha
Classifier: Topic :: Scientific/Engineering
Classifier: Intended Audience :: Science/Research
Classifier: Environment :: Console
Requires-Python: >=3.9
License-File: LICENSE
Requires-Dist: scikit-learn (==1.2.0)
